[
    {
        "text": "“We read to know we're not alone.”",
        "author": "William Nicholson",
        "tags": [
            "misattributed-to-c-s-lewis",
            "reading"
        ]
    },
    {
        "text": "“We read to know we're not alone.”",
        "author": "William Nicholson",
        "tags": [
            "misattributed-to-c-s-lewis",
            "reading"
        ]
    },
    {
        "text": "“We read to know we're not alone.”",
        "author": "William Nicholson",
        "tags": [
            "misattributed-to-c-s-lewis",
            "reading"
        ]
    },
    {
        "text": "“We read to know we're not alone.”",
        "author": "William Nicholson",
        "tags": [
            "misattributed-to-c-s-lewis",
            "reading"
        ]
    }
]